ais_langchain/__init__.py
ais_langchain/ais_tool.py
ais_langchain/ais_tool_enhanced.py
ais_langchain/observability.py
ais_langchain/py.typed
ais_langchain/resilience.py
ais_langchain-0.1.3.dist-info/licenses/LICENSE
ais_langchain-0.1.3.dist-info/METADATA
ais_langchain-0.1.3.dist-info/WHEEL
ais_langchain-0.1.3.dist-info/top_level.txt
ais_langchain-0.1.3.dist-info/RECORD
