Metadata-Version: 2.4
Name: ais-langchain
Version: 0.1.3
Summary: Production-grade LangChain integration for AIS Protocol - Connect AIS agents to LangGraph workflows
Author-email: Mercola Consulting Services <manishk@mercola.com>
Maintainer-email: Mercola Consulting Services <manishk@mercola.com>
License: Apache-2.0
Project-URL: Homepage, https://github.com/ais-protocol/ais-langchain-python
Project-URL: Documentation, https://github.com/ais-protocol/ais-langchain-python#readme
Project-URL: Repository, https://github.com/ais-protocol/ais-langchain-python
Project-URL: Issues, https://github.com/ais-protocol/ais-langchain-python/issues
Keywords: ais-protocol,langchain,langgraph,ai-agents,agent-communication,multi-agent,llm
Classifier: Development Status :: 4 - Beta
Classifier: Intended Audience :: Developers
Classifier: License :: OSI Approved :: Apache Software License
Classifier: Programming Language :: Python :: 3
Classifier: Programming Language :: Python :: 3.9
Classifier: Programming Language :: Python :: 3.10
Classifier: Programming Language :: Python :: 3.11
Classifier: Programming Language :: Python :: 3.12
Classifier: Topic :: Software Development :: Libraries :: Python Modules
Classifier: Topic :: Scientific/Engineering :: Artificial Intelligence
Requires-Python: >=3.9
License-File: LICENSE
Requires-Dist: langchain<1.0.0,>=0.3.0
Requires-Dist: langchain-core<1.0.0,>=0.3.0
Requires-Dist: langgraph<1.0.0,>=0.2.0
Requires-Dist: pydantic>=2.0.0
Requires-Dist: aiohttp>=3.9.0
Provides-Extra: dev
Requires-Dist: pytest>=7.4.0; extra == "dev"
Requires-Dist: pytest-asyncio>=0.21.0; extra == "dev"
Requires-Dist: pytest-cov>=4.1.0; extra == "dev"
Requires-Dist: black>=23.7.0; extra == "dev"
Requires-Dist: ruff>=0.0.280; extra == "dev"
Requires-Dist: mypy>=1.5.0; extra == "dev"
Provides-Extra: examples
Requires-Dist: langchain-openai>=0.1.0; extra == "examples"
Dynamic: license-file
